fstrent_colors/__init__.py
fstrent_colors/fstrent_colors.py
tests/__init__.py
tests/test_fstrent_colors.py
fstrent_colors-1.0.12.dist-info/LICENSE
fstrent_colors-1.0.12.dist-info/METADATA
fstrent_colors-1.0.12.dist-info/WHEEL
fstrent_colors-1.0.12.dist-info/top_level.txt
fstrent_colors-1.0.12.dist-info/RECORD
