Metadata-Version: 2.1
Name: fstrent_colors
Version: 1.0.12
Summary: Enhanced colors options for terminal output
Home-page: https://github.com/wrm3/fstrent_colors
Author: FSTrent
Author-email: wrmartel3@gmail.com
Classifier: Programming Language :: Python :: 3
Classifier: License :: OSI Approved :: MIT License
Classifier: Operating System :: OS Independent
Requires-Python: >=3.6
License-File: LICENSE
Requires-Dist: colorama
